README.rst
setup.py
snfinv.py
snfinv.egg-info/PKG-INFO
snfinv.egg-info/SOURCES.txt
snfinv.egg-info/dependency_links.txt
snfinv.egg-info/entry_points.txt
snfinv.egg-info/requires.txt
snfinv.egg-info/top_level.txt