Metadata-Version: 1.0
Name: snfinv
Version: 0.1.2
Summary: Dynamic ansible inventory for Synnefo IaaS nodes
Home-page: https://github.com/vinilios/snfinv
Author: Kostas Papadimitriou
Author-email: kpap@grnet.gr
License: GPL
Keywords: ansible synnefo provision inventory
Platform: UNKNOWN
